checkspot/__init__.py
checkspot/__main__.py
checkspot/checkspot.py
checkspot-1.0.1.dist-info/DESCRIPTION.rst
checkspot-1.0.1.dist-info/METADATA
checkspot-1.0.1.dist-info/RECORD
checkspot-1.0.1.dist-info/WHEEL
checkspot-1.0.1.dist-info/entry_points.txt
checkspot-1.0.1.dist-info/metadata.json
checkspot-1.0.1.dist-info/top_level.txt
