Metadata-Version: 2.0
Name: checkspot
Version: 1.0.1
Summary: A simple CLI tool to check the spot prices of AWS instances. 
Home-page: http://www.joeyism.com
Author: Joey Sham
Author-email: sham.joey@gmail.com
License: UNKNOWN
Platform: UNKNOWN
Requires-Dist: boto3
Requires-Dist: click
Requires-Dist: terminaltables
